ehn/__init__.py
ehn/_bin/__init__.py
ehn/_bin/parser.py
ehn/db/__init__.py
ehn/db/core.py
ehn/db/data.py
ehn/graph/__init__.py
ehn/graph/standard.py
ehn/graph/vis.py
ehn/parse/__init__.py
ehn/parse/parser.py
ehn/parse/parsetab.py
ehn/parse/node/__init__.py
ehn/parse/node/base.py
ehn/parse/node/entity.py
ehn/parse/node/feature.py
ehn/parse/node/other.py
ehn/parse/node/placeholder.py
ehn/parse/node/reference.py
ehownet-3.0.2.dist-info/LICENSE
ehownet-3.0.2.dist-info/METADATA
ehownet-3.0.2.dist-info/WHEEL
ehownet-3.0.2.dist-info/entry_points.txt
ehownet-3.0.2.dist-info/top_level.txt
ehownet-3.0.2.dist-info/RECORD
