Metadata-Version: 2.1
Name: ehownet
Version: 3.0.2
Summary: E-HowNet Utilities
Home-page: https://ehownet.readthedocs.io
Author: Mu Yang
Author-email: emfomy@gmail.com
License: GPL-3.0
Download-URL: https://ehownet.readthedocs.io/tarball/3.0.2
Platform: linux_x86_64
Classifier: Development Status :: 5 - Production/Stable
Classifier: Environment :: Console
Classifier: Programming Language :: Python
Classifier: Programming Language :: Python :: 3
Classifier: Programming Language :: Python :: 3.6
Classifier: Programming Language :: Python :: 3.7
Classifier: Programming Language :: Python :: 3.8
Classifier: Programming Language :: Python :: 3 :: Only
Classifier: License :: Free for non-commercial use
Classifier: Natural Language :: Chinese (Traditional)
Requires-Dist: ply (>=3.11)
Requires-Dist: treelib (>=1.6.0)
Requires-Dist: wcwidth (>=0.2.5)
Requires-Dist: dataclasses ; python_version < "3.7"
